deloreans/__init__.py
deloreans/api.py
deloreans/app.py
deloreans/date_utils/__init__.py
deloreans/date_utils/common.py
deloreans/date_utils/date_granularity.py
deloreans/date_utils/date_range.py
deloreans/date_utils/offset_granularity.py
deloreans/exceptions.py
deloreans-0.2.0.dist-info/LICENSE
deloreans-0.2.0.dist-info/METADATA
deloreans-0.2.0.dist-info/WHEEL
deloreans-0.2.0.dist-info/RECORD
